AUTHORS
LICENSE
MANIFEST.in
README.rst
requirements.txt
setup.cfg
setup.py
lib/dbusx/__init__.py
lib/dbusx/_dbus.c
lib/dbusx/connection.py
lib/dbusx/exception.py
lib/dbusx/message.py
lib/dbusx/object.py
lib/dbusx/proxy.py
lib/dbusx/util.py
lib/dbusx/test/__init__.py
lib/dbusx/test/dbus.conf
lib/dbusx/test/logging.conf
lib/dbusx/test/test_connection.py
lib/dbusx/test/test_dbusx.py
lib/dbusx/test/test_loop.py
lib/dbusx/test/test_message.py
lib/dbusx/test/test_object.py
lib/python_dbusx.egg-info/PKG-INFO
lib/python_dbusx.egg-info/SOURCES.txt
lib/python_dbusx.egg-info/dependency_links.txt
lib/python_dbusx.egg-info/requires.txt
lib/python_dbusx.egg-info/top_level.txt