Metadata-Version: 1.1
Name: python-dbusx
Version: 0.9
Summary: An alternate interface to D-BUS supporting evented IO
Home-page: https://github.com/geertj/python-dbusx
Author: Geert Jansen
Author-email: geertj@gmail.com
License: MIT
Platform: UNKNOWN
Classifier: Development Status :: 4 - Beta
Classifier: License :: OSI Approved :: MIT License
Classifier: Operating System :: POSIX
Classifier: Programming Language :: Python :: 2.6
Classifier: Programming Language :: Python :: 2.7
Classifier: Programming Language :: Python :: 3.2
Classifier: Programming Language :: Python :: 3.3
